basic_calculator/__init__.py
basic_calculator/basic.py
basic_calculator/medium.py
cli_calculator/__init__.py
cli_calculator/main.py
cli_calculator-0.0.2.post1.dist-info/licenses/LICENSE
cli_calculator-0.0.2.post1.dist-info/METADATA
cli_calculator-0.0.2.post1.dist-info/WHEEL
cli_calculator-0.0.2.post1.dist-info/entry_points.txt
cli_calculator-0.0.2.post1.dist-info/top_level.txt
cli_calculator-0.0.2.post1.dist-info/RECORD
