Metadata-Version: 2.4
Name: cli_calculator
Version: 0.0.2.post1
Summary: A simple terminal calculator supporting basic arithmetic operations.
Home-page: https://github.com/robson-k/cli-calculator
Author: Robson
License: MIT
Requires-Python: >=3.8
License-File: LICENSE
Dynamic: author
Dynamic: description
Dynamic: description-content-type
Dynamic: home-page
Dynamic: license
Dynamic: license-file
Dynamic: requires-python
Dynamic: summary
